.travis.yml
AUTHORS
CONTRIBUTORS.md
EXAMPLES.md
LICENSE
MANIFEST.in
README.md
codecov.yml
conductor-requirements.txt
conductor-requirements.yml
release.yml
requirements.txt
setup.py
ansible_container.egg-info/PKG-INFO
ansible_container.egg-info/SOURCES.txt
ansible_container.egg-info/dependency_links.txt
ansible_container.egg-info/entry_points.txt
ansible_container.egg-info/not-zip-safe
ansible_container.egg-info/requires.txt
ansible_container.egg-info/top_level.txt
container/__init__.py
container/cli.py
container/config.py
container/core.py
container/engine.py
container/exceptions.py
container/docker/__init__.py
container/docker/config.py
container/docker/deploy.py
container/docker/engine.py
container/docker/importer.py
container/docker/secrets.py
container/docker/files/conductor-requirements.txt
container/docker/files/conductor-requirements.yml
container/docker/files/get-pip.py
container/docker/files/setup.py
container/docker/templates/conductor-local-dockerfile.j2
container/docker/templates/conductor-src-dockerfile.j2
container/k8s/__init__.py
container/k8s/base_config.py
container/k8s/base_deploy.py
container/k8s/base_engine.py
container/k8s/config.py
container/k8s/deploy.py
container/k8s/engine.py
container/openshift/__init__.py
container/openshift/config.py
container/openshift/deploy.py
container/openshift/engine.py
container/templates/ansible-container-inventory.py
container/templates/ansible-dockerfile.j2
container/templates/ansible.cfg
container/templates/builder.sh
container/templates/compose_versioned.j2.yml
container/templates/hosts.j2
container/templates/install-docker-compose.j2.yml
container/templates/restart-docker-compose.j2.yml
container/templates/run-docker-compose.j2.yml
container/templates/stop-docker-compose.j2.yml
container/templates/wait_on_host.py
container/templates/init/ansible-requirements.j2.txt
container/templates/init/ansible.j2.cfg
container/templates/init/container.j2.yml
container/templates/init/meta.j2.yml
container/templates/init/requirements.j2.yml
container/templates/role/.travis.j2.yml
container/templates/role/README.j2.md
container/templates/role/defaults/main.j2.yml
container/templates/role/meta/main.j2.yml
container/templates/role/test/test.j2.yml
container/utils/__init__.py
container/utils/_text.py
