Metadata-Version: 1.0
Name: ansible-container
Version: 0.9.2
Summary: Ansible Container empowers you to orchestrate, build, run, and ship Docker images built from Ansible playbooks.
Home-page: https://github.com/ansible/ansible-container
Author: Joshua "jag" Ginsberg, Chris Houseknecht, and others (See AUTHORS file for contributors)
Author-email: jag@ansible.com
License: LGPLv3 (See LICENSE file for terms)
Platform: UNKNOWN
